{
  "$schema": "https://xml.riverscapes.xyz/Symbology/web/vector.schema.json",
  "legend": [
    ["rgb(241, 238, 246)", "0%"],
    ["rgb(212, 185, 218)", "0 - 5%"],
    ["rgb(201, 148, 199)", "5 - 15%"],
    ["rgb(223, 101, 176)", "15 - 30%"],
    ["rgb(221, 28, 119)", "30 - 60%"],
    ["rgb(152, 0, 67)", "> 60%"]
  ],
  "layerStyles": [
        {
            "id": "dgo-metrics-sample-byd148",
            "type": "fill",
            "source": "composite",
            "source-layer": "dgo_metrics_sample-byd148",
            "layout": {},
            "paint": {
                "fill-color": [
                "interpolate",
                ["linear"],
                ["get", "lf_exotic_tree_shrub_prop"],
                0,
                "rgb(241, 238, 246)",
                0.00001,
                "rgb(241, 238, 246)",
                0.00002,
                "rgb(212, 185, 218)",
                0.05,
                "rgb(212, 185, 218)",
                0.0501,
                "rgb(201, 148, 199)",
                0.15,
                "rgb(201, 148, 199)",
                0.1501,
                "rgb(223, 101, 176)",
                0.3,
                "rgb(223, 101, 176)",
                0.3001,
                "rgb(221, 28, 119)",
                0.6,
                "rgb(221, 28, 119)",
                0.6001,
                "rgb(152, 0, 67)",
                1,
                "rgb(152, 0, 67)"
            ],
                "fill-opacity": 0.6
            }
        },
        {
            "id": "outline",
            "type": "line",
            "source": "composite",
            "source-layer": "dgo_metrics_sample-byd148",
            "paint": {"line-width": 0.1}
        }
    ]
}