{
  "$schema": "https://xml.riverscapes.xyz/Symbology/web/vector.schema.json",
  "legend": [
    [
      "rgb(255, 255, 0)",
      "-2.44 - 0.58"
    ],
    [
      "rgb(154, 205, 50)",
      "0.58 - 0.94"
    ],
    [
      "rgb(34, 139, 34)",
      "0.94 - 1.43"
    ],
    [
      "rgb(255, 140, 0)",
      "1.43 - 2.39"
    ],
    [
      "rgb(220, 20, 60)",
      "2.39 - 9.38"
    ]
  ],
  "layerStyles": [
    {
      "id": "rme-igos-sample-2f60tk",
      "type": "circle",
      "source": "composite",
      "source-layer": "RME_igos_sample-2f60tk",
      "layout": {},
      "paint": {
        "circle-color": [
          "step",
          [
            "get",
            "Grad"
          ],
          "rgb(255, 255, 0)",
          0.576494703382,
          "rgb(154, 205, 50)",
          0.93546836344,
          "rgb(34, 139, 34)",
          1.4301536814,
          "rgb(255, 140, 0)",
          2.39295224121,
          "rgb(220, 20, 60)"
        ],
        "circle-radius": [
          "interpolate",
          [
            "linear"
          ],
          [
            "zoom"
          ],
          10,
          3,
          11,
          5,
          13.5,
          7,
          15,
          9,
          22,
          11
        ]
      }
    }
  ]
}