{
  "$schema": "https://xml.riverscapes.xyz/Symbology/web/vector.schema.json",
  "legend": [
    ["#ffffff", "0%"],
    ["#ffff88", "0% to 10%"],
    ["#fed98e", "10% to 25%"],
    ["#fe9929", "25% to 50%"],
    ["#bc1000", "50% to 75%"],
    ["#85000c", "> 75%"]
  ],
  "layerStyles": [
    {
      "id": "Fill",
      "type": "fill",
      "source": "composite",
      "source-layer": "vbet_dgos-b595ip",
      "slot": "",
      "layout": {},
      "paint": {
          "fill-color": [
              "interpolate",
              ["linear"],
              ["get", "elevated_floodplain_prop"],
              0,
              "#ffffff",
              0.000001,
              "#ffffff",
              0.000002,
              "#ffff88",
              0.1,
              "#ffff88",
              0.100001,
              "#fed98e",
              0.25,
              "#fed98e",
              0.250001,
              "#fe9929",
              0.50,
              "#fe9929",
              0.500001,
              "#bc1000",
              0.75,
              "#bc1000",
              0.7500001,
              "#85000c",
              2,
              "#85000c"
          ]
      }
  },
  {
      "id": "Outline",
      "type": "line",
      "source": "composite",
      "source-layer": "vbet_dgos-b595ip",
      "layout": {},
      "paint": {"line-width": 0.5}
  }
  ]
}